free/__init__.py
free/settings.py
free/skeleton.py
free/urls.py
free/wsgi.py
free-0.0.2.dist-info/DESCRIPTION.rst
free-0.0.2.dist-info/METADATA
free-0.0.2.dist-info/RECORD
free-0.0.2.dist-info/WHEEL
free-0.0.2.dist-info/metadata.json
free-0.0.2.dist-info/top_level.txt
